boxi/__init__.py
boxi/__main__.py
boxi/adwaita_palette.py
boxi/agent.py
boxi/app.py
boxi/monitor.py
boxi/toolbox_run.py
boxi-5.data/data/share/applications/dev.boxi.Boxi.desktop
boxi-5.data/data/share/dbus-1/services/dev.boxi.Boxi.service
boxi-5.data/data/share/glib-2.0/schemas/dev.boxi.gschema.xml
boxi-5.data/data/share/icons/hicolor/scalable/apps/dev.boxi.Boxi.svg
boxi-5.data/data/share/icons/hicolor/symbolic/apps/dev.boxi.Boxi-symbolic.svg
boxi-5.data/data/share/metainfo/dev.boxi.Boxi.metainfo.xml
boxi-5.dist-info/METADATA
boxi-5.dist-info/WHEEL
boxi-5.dist-info/entry_points.txt
boxi-5.dist-info/top_level.txt
boxi-5.dist-info/RECORD
