Metadata-Version: 2.1
Name: boxi
Version: 5
Summary: A terminal emulator for use with Toolbox
Author-email: Allison Karlitskaya <allison.karlitskaya@redhat.com>
Project-URL: Home, https://github.com/allisonkarlitskaya/boxi/
Classifier: License :: OSI Approved :: GNU General Public License v3 or later (GPLv3+)
